[
    {
        "symbol": "MAINIDX31AUG2320000PE",
        "LTP": "132795",
        "LTQ": "100",
        "totalTradedVolume": "0",
        "bestBid": "96000",
        "bestAsk": "159510",
        "bestBidQty": "150",
        "bestAskQty": "100",
        "openInterest": "0",
        "timestamp": "Mon Jul 03 16:38:34 IST 2023",
        "sequence": "1229",
        "prevClosePrice": "6150",
        "prevOpenInterest": "5900"
    },
    {
        "symbol": "MAINIDX06JUL2316900CE",
        "LTP": "164765",
        "LTQ": "0",
        "totalTradedVolume": "0",
        "bestBid": "129040",
        "bestAsk": "215650",
        "bestBidQty": "1750",
        "bestAskQty": "1750",
        "openInterest": "0",
        "timestamp": "Mon Jul 03 16:38:34 IST 2023",
        "sequence": "1230",
        "prevClosePrice": "6150",
        "prevOpenInterest": "6150"
    },
    {
        "symbol": "MAINIDX06JUL2319250CE",
        "LTP": "185",
        "LTQ": "78500",
        "totalTradedVolume": "78500",
        "bestBid": "185",
        "bestAsk": "190",
        "bestBidQty": "2900",
        "bestAskQty": "9100",
        "openInterest": "353350",
        "timestamp": "Mon Jul 03 16:38:34 IST 2023",
        "sequence": "1231",
        "prevClosePrice": "61500",
        "prevOpenInterest": "41300"
    },
    {
        "symbol": "FINANCIALS04JUL2319250CE",
        "LTP": "20515",
        "LTQ": "21880",
        "totalTradedVolume": "21880",
        "bestBid": "20515",
        "bestAsk": "20570",
        "bestBidQty": "40",
        "bestAskQty": "40",
        "openInterest": "67760",
        "timestamp": "Mon Jul 03 16:38:34 IST 2023",
        "sequence": "1232",
        "prevClosePrice": "61920",
        "prevOpenInterest": "24360"
    },
    {
        "symbol": "MAINIDX27JUL2319350PE",
        "LTP": "72615",
        "LTQ": "0",
        "totalTradedVolume": "0",
        "bestBid": "71860",
        "bestAsk": "74275",
        "bestBidQty": "200",
        "bestAskQty": "100",
        "openInterest": "0",
        "timestamp": "Mon Jul 03 16:38:34 IST 2023",
        "sequence": "1233",
        "prevClosePrice": "6200",
        "prevOpenInterest": "5600"
    },
    {
        "symbol": "MAINIDX06JUL2316700CE",
        "LTP": "47000",
        "LTQ": "150",
        "totalTradedVolume": "150",
        "bestBid": "45975",
        "bestAsk": "48490",
        "bestBidQty": "50",
        "bestAskQty": "75",
        "openInterest": "5725",
        "timestamp": "Mon Jul 03 16:38:34 IST 2023",
        "sequence": "1235",
        "prevClosePrice": "6250",
        "prevOpenInterest": "2775"
    },
    {
        "symbol": "ALLBANKS27JUL2340800PE",
        "LTP": "4240",
        "LTQ": "0",
        "totalTradedVolume": "0",
        "bestBid": "3005",
        "bestAsk": "0",
        "bestBidQty": "25",
        "bestAskQty": "0",
        "openInterest": "0",
        "timestamp": "Mon Jul 03 16:38:34 IST 2023",
        "sequence": "1236",
        "prevClosePrice": "6300",
        "prevOpenInterest": "0"
    },
    {
        "symbol": "MAINIDX06JUL2316550PE",
        "LTP": "120",
        "LTQ": "15800",
        "totalTradedVolume": "15800",
        "bestBid": "114",
        "bestAsk": "120",
        "bestBidQty": "1800",
        "bestAskQty": "11650",
        "openInterest": "88300",
        "timestamp": "Mon Jul 03 16:38:34 IST 2023",
        "sequence": "1237",
        "prevClosePrice": "630450",
        "prevOpenInterest": "48550"
    },
    {
        "symbol": "ALLBANKS20JUL2343900PE",
        "LTP": "41900",
        "LTQ": "75",
        "totalTradedVolume": "75",
        "bestBid": "41190",
        "bestAsk": "43870",
        "bestBidQty": "500",
        "bestAskQty": "50",
        "openInterest": "1200",
        "timestamp": "Mon Jul 03 16:38:34 IST 2023",
        "sequence": "1238",
        "prevClosePrice": "6325",
        "prevOpenInterest": "1725"
    },
    {
        "symbol": "MAINIDX06JUL2316600PE",
        "LTP": "120",
        "LTQ": "8800",
        "totalTradedVolume": "8800",
        "bestBid": "120",
        "bestAsk": "125",
        "bestBidQty": "6950",
        "bestAskQty": "21900",
        "openInterest": "176700",
        "timestamp": "Mon Jul 03 16:38:34 IST 2023",
        "sequence": "1239",
        "prevClosePrice": "633300",
        "prevOpenInterest": "131250"
    },
    {
        "symbol": "MAINIDX27JUL2319050PE",
        "LTP": "46440",
        "LTQ": "150",
        "totalTradedVolume": "150",
        "bestBid": "43310",
        "bestAsk": "47435",
        "bestBidQty": "150",
        "bestAskQty": "50",
        "openInterest": "2250",
        "timestamp": "Mon Jul 03 16:38:34 IST 2023",
        "sequence": "1240",
        "prevClosePrice": "6350",
        "prevOpenInterest": "6300"
    },
    {
        "symbol": "MAINIDX06JUL2318300CE",
        "LTP": "28870",
        "LTQ": "62150",
        "totalTradedVolume": "62150",
        "bestBid": "28850",
        "bestAsk": "28955",
        "bestBidQty": "250",
        "bestAskQty": "650",
        "openInterest": "692450",
        "timestamp": "Mon Jul 03 16:38:34 IST 2023",
        "sequence": "1241",
        "prevClosePrice": "63500",
        "prevOpenInterest": "58200"
    },
    {
        "symbol": "ALLBANKS13JUL2342100PE",
        "LTP": "3435",
        "LTQ": "125",
        "totalTradedVolume": "125",
        "bestBid": "3390",
        "bestAsk": "3715",
        "bestBidQty": "25",
        "bestAskQty": "25",
        "openInterest": "4050",
        "timestamp": "Mon Jul 03 16:38:34 IST 2023",
        "sequence": "1242",
        "prevClosePrice": "6375",
        "prevOpenInterest": "175"
    },
    {
        "symbol": "FINANCIALS11JUL2318600PE",
        "LTP": "2980",
        "LTQ": "0",
        "totalTradedVolume": "0",
        "bestBid": "655",
        "bestAsk": "0",
        "bestBidQty": "40",
        "bestAskQty": "0",
        "openInterest": "0",
        "timestamp": "Mon Jul"
    },
    {
        "03 16:38:34 IST 2023": "",
        "sequence": "1243",
        "prevClosePrice": "640",
        "prevOpenInterest": "0"
    },
    {
        "symbol": "MAINIDX20JUL2318100CE",
        "LTP": "54035",
        "LTQ": "0",
        "totalTradedVolume": "0",
        "bestBid": "44705",
        "bestAsk": "54935",
        "bestBidQty": "200",
        "bestAskQty": "200",
        "openInterest": "0",
        "timestamp": "Mon Jul 03 16:38:34 IST 2023",
        "sequence": "1244",
        "prevClosePrice": "6400",
        "prevOpenInterest": "2900"
    },
    {
        "symbol": "MAINIDX27JUL2317650CE",
        "LTP": "95500",
        "LTQ": "0",
        "totalTradedVolume": "0",
        "bestBid": "97640",
        "bestAsk": "99245",
        "bestBidQty": "100",
        "bestAskQty": "50",
        "openInterest": "0",
        "timestamp": "Mon Jul 03 16:38:34 IST 2023",
        "sequence": "1245",
        "prevClosePrice": "6400",
        "prevOpenInterest": "5750"
    },
    {
        "symbol": "ALLBANKS06JUL2349500CE",
        "LTP": "305",
        "LTQ": "48750",
        "totalTradedVolume": "48750",
        "bestBid": "295",
        "bestAsk": "305",
        "bestBidQty": "3375",
        "bestAskQty": "3375",
        "openInterest": "105800",
        "timestamp": "Mon Jul 03 16:38:34 IST 2023",
        "sequence": "1246",
        "prevClosePrice": "64225",
        "prevOpenInterest": "24925"
    },
    {
        "symbol": "MAINIDX26OCT2314000PE",
        "LTP": "875",
        "LTQ": "0",
        "totalTradedVolume": "0,"
    },
    {
        "bestBid": "500",
        "bestAsk": "0",
        "bestBidQty": "4150",
        "bestAskQty": "0",
        "openInterest": "0",
        "timestamp": "Mon Jul 03 16:38:34 IST 2023",
        "sequence": "1247",
        "prevClosePrice": "6450",
        "prevOpenInterest": "0"
    },
    {
        "symbol": "MAINIDX06JUL2316750PE",
        "LTP": "125",
        "LTQ": "3700",
        "totalTradedVolume": "3700",
        "bestBid": "114",
        "bestAsk": "125",
        "bestBidQty": "5400",
        "bestAskQty": "6250",
        "openInterest": "6700",
        "timestamp": "Mon Jul 03 16:38:34 IST 2023",
        "sequence": "1248",
        "prevClosePrice": "64650",
        "prevOpenInterest": "20300"
    },
    {
        "symbol": "ALLBANKS13JUL2348500CE",
        "LTP": "645",
        "LTQ": "0",
        "totalTradedVolume": "0",
        "bestBid": "380",
        "bestAsk": "620",
        "bestBidQty": "375",
        "bestAskQty": "150",
        "openInterest": "0",
        "timestamp": "Mon Jul 03 16:38:34 IST 2023",
        "sequence": "1249",
        "prevClosePrice": "6475",
        "prevOpenInterest": "1075"
    },
    {
        "symbol": "FINANCIALS04JUL2320500PE",
        "LTP": "107740",
        "LTQ": "0",
        "totalTradedVolume": "0",
        "bestBid": "104730",
        "bestAsk": "110015",
        "bestBidQty": "80",
        "bestAskQty": "1280",
        "openInterest": "0",
        "timestamp": "Mon Jul 03 16:38:34 IST 2023",
        "sequence": "1250",
        "prevClosePrice": "6480",
        "prevOpenInterest": "6480"
    },
    {
        "symbol": "ALLBANKS13JUL2343400CE",
        "LTP": "73725",
        "LTQ": "0",
        "totalTradedVolume": "0",
        "bestBid": "83190",
        "bestAsk": "86585",
        "bestBidQty": "50",
        "bestAskQty": "50",
        "openInterest": "0",
        "timestamp": "Mon Jul 03 16:38:34 IST 2023",
        "sequence": "1251",
        "prevClosePrice": "6500",
        "prevOpenInterest": "4200"
    },
    {
        "symbol": "MAINIDX27JUL2317200CE",
        "LTP": "137205",
        "LTQ": "0",
        "totalTradedVolume": "0",
        "bestBid": "141200",
        "bestAsk": "142850",
        "bestBidQty": "100",
        "bestAskQty": "100",
        "openInterest": "0",
        "timestamp": "Mon Jul 03 16:38:34 IST 2023",
        "sequence": "1252",
        "prevClosePrice": "6500",
        "prevOpenInterest": "7100"
    },
    {
        "symbol": "MAINIDX27JUL2317000PE",
        "LTP": "860",
        "LTQ": "500",
        "totalTradedVolume": "500",
        "bestBid": "860",
        "bestAsk": "885",
        "bestBidQty": "1550",
        "bestAskQty": "50",
        "openInterest": "3784350",
        "timestamp": "Mon Jul 03 16:38:34 IST 2023",
        "sequence": "1253",
        "prevClosePrice": "65050",
        "prevOpenInterest": "29650"
    },
    {
        "symbol": "ALLBANKS06JUL2347000CE",
        "LTP": "520",
        "LTQ": "165225",
        "totalTradedVolume": "165225",
        "bestBid": "515",
        "bestAsk": "520",
        "bestBidQty": "50",
        "bestAskQty": "7375",
        "openInterest": "1421750,"
    },
    {
        "timestamp": "Mon Jul 03 16:38:34 IST 2023",
        "sequence": "1254",
        "prevClosePrice": "65175",
        "prevOpenInterest": "38475"
    },
    {
        "symbol": "ALLBANKS06JUL2343700PE",
        "LTP": "16330",
        "LTQ": "305800",
        "totalTradedVolume": "305800",
        "bestBid": "16180",
        "bestAsk": "16235",
        "bestBidQty": "25",
        "bestAskQty": "50",
        "openInterest": "494400",
        "timestamp": "Mon Jul 03 16:38:34 IST 2023",
        "sequence": "1255",
        "prevClosePrice": "65225",
        "prevOpenInterest": "46625"
    },
    {
        "symbol": "ALLBANKS13JUL2344800PE",
        "LTP": "103509",
        "LTQ": "0",
        "totalTradedVolume": "0",
        "bestBid": "85440",
        "bestAsk": "88440",
        "bestBidQty": "50",
        "bestAskQty": "50",
        "openInterest": "0",
        "timestamp": "Mon Jul 03 16:38:34 IST 2023",
        "sequence": "1256",
        "prevClosePrice": "6525",
        "prevOpenInterest": "4200"
    },
    {
        "symbol": "ALLBANKS06JUL2344800CE",
        "LTP": "5485",
        "LTQ": "219325",
        "totalTradedVolume": "219325",
        "bestBid": "5445",
        "bestAsk": "5470",
        "bestBidQty": "150",
        "bestAskQty": "375",
        "openInterest": "730050",
        "timestamp": "Mon Jul 03 16:38:34 IST 2023",
        "sequence": "1257",
        "prevClosePrice": "65425",
        "prevOpenInterest": "37675"
    }
]